EightBitTransit/TransitingImage.py
EightBitTransit/__init__.py
EightBitTransit/cGridFunctions.py
EightBitTransit/gpu_methods.py
EightBitTransit/inversion.py
EightBitTransit/mats.py
EightBitTransit/misc.py
EightBitTransit/pep8.py
EightBitTransit/pixeloverlap.py
EightBitTransit/transitmodel.py
EightBitTransit-2.1.0.dist-info/AUTHORS.rst
EightBitTransit-2.1.0.dist-info/LICENSE
EightBitTransit-2.1.0.dist-info/METADATA
EightBitTransit-2.1.0.dist-info/WHEEL
EightBitTransit-2.1.0.dist-info/top_level.txt
EightBitTransit-2.1.0.dist-info/RECORD
