Metadata-Version: 2.1
Name: EightBitTransit
Version: 2.1.0
Summary: Shadow imaging of transiting objects
Home-page: https://github.com/d-giles/EightBitTransitGPU
Author: Daniel Giles (Orig. Emily Sandford)
Author-email: daniel.k.giles@gmail.com
License: MIT
Platform: UNKNOWN
Requires-Python: >=3.6
License-File: LICENSE
License-File: AUTHORS.rst
Requires-Dist: matplotlib
Requires-Dist: numpy
Requires-Dist: scipy
Requires-Dist: imageio
Requires-Dist: numba
Requires-Dist: jupyterlab
